super_eureka/__init__.py
super_eureka/logging.py
super_eureka-0.0.1.dist-info/METADATA
super_eureka-0.0.1.dist-info/WHEEL
super_eureka-0.0.1.dist-info/licenses/LICENSE
super_eureka-0.0.1.dist-info/RECORD
