Metadata-Version: 2.1
Name: super_eureka
Version: 0.0.1
Summary: A logging library without hassle.
Project-URL: Homepage, https://github.com/wesley950/super-eureka
Project-URL: Bug Tracker, https://github.com/wesley950/super-eureka/issues
Author-email: Wesley Barros <wesleybarros950@gmail.com>
License-File: LICENSE
Classifier: License :: OSI Approved :: MIT License
Classifier: Operating System :: OS Independent
Classifier: Programming Language :: Python :: 3
Requires-Python: >=3.7
